mwbzcl/__init__.py
mwbzcl/client.py
mwbzcl-1.0.6.dist-info/LICENSE
mwbzcl-1.0.6.dist-info/METADATA
mwbzcl-1.0.6.dist-info/WHEEL
mwbzcl-1.0.6.dist-info/entry_points.txt
mwbzcl-1.0.6.dist-info/top_level.txt
mwbzcl-1.0.6.dist-info/RECORD
