Metadata-Version: 2.1
Name: mwbzcl
Version: 1.0.6
Summary: A command-line client to interact with the MalwareBazaar API
Home-page: https://github.com/larsborn/MalwareBazaarClient
Author: Lars Wallenborn
Author-email: lars@wallenborn.net
Project-URL: Bug Tracker, https://github.com/larsborn/MalwareBazaarClient/issues
Classifier: Development Status :: 5 - Production/Stable
Classifier: Environment :: Console
Classifier: Operating System :: OS Independent
Classifier: Programming Language :: Python :: 3
Classifier: Topic :: Security
Classifier: Topic :: Utilities
Classifier: Intended Audience :: Developers
Classifier: Intended Audience :: End Users/Desktop
Classifier: Intended Audience :: Information Technology
Classifier: Intended Audience :: Science/Research
Classifier: License :: OSI Approved :: MIT License
Requires-Python: >=3.7
License-File: LICENSE
Requires-Dist: requests
Requires-Dist: pyzipper
